setup.py
python_snss.egg-info/PKG-INFO
python_snss.egg-info/SOURCES.txt
python_snss.egg-info/dependency_links.txt
python_snss.egg-info/not-zip-safe
python_snss.egg-info/requires.txt
python_snss.egg-info/top_level.txt
snss/__init__.py
snss/constants.py