Metadata-Version: 1.0
Name: python-snss
Version: 0.1
Summary: Parse Google Chrome SNSS files via 
Home-page: http://github.com/deactivated/python-snss
Author: Mike Spindel
Author-email: mike@spindel.is
License: MIT
Keywords: snss chrome session
Platform: UNKNOWN
Classifier: Development Status :: 4 - Beta
Classifier: License :: OSI Approved :: MIT License
Classifier: Intended Audience :: Developers
Classifier: Natural Language :: English
Classifier: Programming Language :: Python
